bestmcp/__init__.py
bestmcp/cli.py
bestmcp/agents/base.py
bestmcp/agents/runner.py
bestmcp/agents/simple_openai_agent.py
bestmcp/core/__init__.py
bestmcp/core/base_protocol.py
bestmcp/core/base_protocol_adapter.py
bestmcp/core/client.py
bestmcp/core/connector.py
bestmcp/core/network.py
bestmcp/core/system_commands.py
bestmcp/launchers/__init__.py
bestmcp/launchers/discovery_connector.py
bestmcp/launchers/network_launcher.py
bestmcp/launchers/terminal_console.py
bestmcp/models/__init__.py
bestmcp/models/manifest.py
bestmcp/models/message_thread.py
bestmcp/models/messages.py
bestmcp/models/network_config.py
bestmcp/models/network_profile.py
bestmcp/models/tool.py
bestmcp/protocols/__init__.py
bestmcp/protocols/communication/__init__.py
bestmcp/protocols/communication/simple_messaging/__init__.py
bestmcp/protocols/communication/simple_messaging/adapter.py
bestmcp/protocols/communication/simple_messaging/protocol.py
bestmcp/protocols/communication/simple_messaging/protocol_manifest.json
bestmcp/protocols/discovery/__init__.py
bestmcp/protocols/discovery/agent_discovery/__init__.py
bestmcp/protocols/discovery/agent_discovery/adapter.py
bestmcp/protocols/discovery/agent_discovery/protocol.py
bestmcp/protocols/discovery/agent_discovery/protocol_manifest.json
bestmcp/utils/__init__.py
bestmcp/utils/message_util.py
bestmcp/utils/network_discovey.py
bestmcp/utils/protocol_loaders.py
bestmcp-0.4.0.dist-info/licenses/LICENSE
openagents/__init__.py
openagents/cli.py
openagents/agents/base.py
openagents/agents/runner.py
openagents/agents/simple_openai_agent.py
openagents/core/__init__.py
openagents/core/base_protocol.py
openagents/core/base_protocol_adapter.py
openagents/core/client.py
openagents/core/connector.py
openagents/core/network.py
openagents/core/system_commands.py
openagents/launchers/__init__.py
openagents/launchers/discovery_connector.py
openagents/launchers/network_launcher.py
openagents/launchers/terminal_console.py
openagents/models/__init__.py
openagents/models/manifest.py
bestmcp-0.4.0.dist-info/METADATA
bestmcp-0.4.0.dist-info/WHEEL
bestmcp-0.4.0.dist-info/entry_points.txt
bestmcp-0.4.0.dist-info/top_level.txt
bestmcp-0.4.0.dist-info/RECORD
